pyturbo/__init__.py
pyturbo/face_detection/__init__.py
pyturbo/face_detection/MTCNN_tf/__init__.py
pyturbo/face_detection/MTCNN_tf/detect_face.py
pyturbo/face_detection/MTCNN_tf/mtcnn.py
pyturbo-18.7.27.dist-info/METADATA
pyturbo-18.7.27.dist-info/RECORD
pyturbo-18.7.27.dist-info/WHEEL
pyturbo-18.7.27.dist-info/top_level.txt
