Metadata-Version: 2.1
Name: pyturbo
Version: 18.7.27
Summary: This project contains a variety of different python packages
Home-page: https://github.com/aikudexiaohai/pyturbo
Author: aikudexiaohai
Author-email: 1052220704@qq.com
Maintainer: aikudexiaohai
Maintainer-email: 1052220704@qq.com
License: BSD License
Platform: all
Classifier: Programming Language :: Python :: 3.5
Requires-Dist: tensorflow
Requires-Dist: opencv-python
Requires-Dist: numpy
Requires-Dist: six
